{
  "last_updated": "2026-01-19T16:54:17.157519Z",
  "total_matches": 1,
  "matches": [
    {
      "title": "Brighton vs Bournemouth",
      "url": "https://ovogoaal.com/match-updates/brighton-vs-bournemouth/",
      "time": "21:00",
      "category": "laliga",
      "first_level_iframes": [
        "https://matchify.zip/home/blog1/"
      ],
      "stream_urls": [
        "https://matchify.zip/1111.php"
      ],
      "stream_count": 1,
      "iframe_details": [
        {
          "url": "https://matchify.zip/home/blog1/",
          "nested_iframes": [
            {
              "url": "https://matchify.zip/1111.php",
              "nested_iframes": [],
              "stream_urls": []
            }
          ],
          "stream_urls": [
            "https://matchify.zip/1111.php"
          ]
        }
      ]
    }
  ]
}